convertflac/__init__.py
convertflac/main.py
convertflac/version_getter.py
convertflac-1.0.4.dist-info/METADATA
convertflac-1.0.4.dist-info/WHEEL
convertflac-1.0.4.dist-info/entry_points.txt
convertflac-1.0.4.dist-info/licenses/LICENSE
convertflac-1.0.4.dist-info/RECORD
