Metadata-Version: 2.1
Name: convertflac
Version: 1.0.4
Summary: Convert FLAC audio files into ALAC or MP3 files.
Project-URL: Homepage, https://github.com/haru52/convertflac#readme
Project-URL: Bug Tracker, https://github.com/haru52/convertflac/issues
Project-URL: Repository, https://github.com/haru52/convertflac.git
Author: haru
License-Expression: MIT
License-File: LICENSE
Keywords: alac,audio,cli,converter,encoder,flac,mp3
Classifier: License :: OSI Approved :: MIT License
Classifier: Operating System :: OS Independent
Classifier: Programming Language :: Python :: 3
Requires-Python: ~=3.11
Requires-Dist: click~=8.1
